libname/__init__.py
libname/algebra.py
addpkg-0.1.dist-info/METADATA
addpkg-0.1.dist-info/WHEEL
addpkg-0.1.dist-info/top_level.txt
addpkg-0.1.dist-info/RECORD
