Metadata-Version: 2.1
Name: addpkg
Version: 0.1
Summary: Lorem ipsum...
Author: Pierre BEJIAN
Author-email: pierre.bejian@gmail.com
Requires-Dist: numpy
